{
  "timestamp": "2025-06-17 19:37:09",
  "auditSummary": {
    "timestamp": "2025-06-17 19:37:09",
    "totalChecks": 20,
    "totalPassed": 19,
    "passRate": 95,
    "categories": [
      {
        "category": "ファイルアクセス",
        "checks": 5,
        "passed": 5
      },
      {
        "category": "データ整合性",
        "checks": 7,
        "passed": 7
      },
      {
        "category": "設計書制約遵守",
        "checks": 5,
        "passed": 5
      },
      {
        "category": "コードセキュリティ",
        "checks": 3,
        "passed": 2
      }
    ]
  },
  "securityLog": [
    {
      "type": "file_access_security",
      "checks": [
        {
          "check": "inputディレクトリアクセス",
          "status": "safe",
          "details": "アクセス権限が適切に設定されています"
        },
        {
          "check": "データベースファイル保護: archive-index.db",
          "status": "safe",
          "details": "ファイルサイズ: 32768 bytes"
        },
        {
          "check": "データベースファイル保護: learning.db",
          "status": "safe",
          "details": "ファイルサイズ: 106496 bytes"
        },
        {
          "check": "データベースファイル保護: profiles.db",
          "status": "safe",
          "details": "ファイルサイズ: 24576 bytes"
        },
        {
          "check": "outputディレクトリセキュリティ",
          "status": "safe",
          "details": "適切なアクセス制御が設定されています"
        }
      ],
      "timestamp": "2025-06-17 19:37:09"
    },
    {
      "type": "data_integrity",
      "checks": [
        {
          "check": "データベーステーブル数",
          "value": 6,
          "expected": 6,
          "status": "safe"
        },
        {
          "check": "学習パターン数",
          "value": 14,
          "status": "safe"
        },
        {
          "check": "NULL値検証",
          "value": 0,
          "status": "safe"
        },
        {
          "check": "ファイル内容検証: comprehensive_test_data.txt",
          "status": "safe",
          "size": 432
        },
        {
          "check": "ファイル内容検証: constraint_violation_fix.txt",
          "status": "safe",
          "size": 358
        },
        {
          "check": "ファイル内容検証: interactive_workflow_test.txt",
          "status": "safe",
          "size": 423
        },
        {
          "check": "ファイル内容検証: zero-base-test.txt",
          "status": "safe",
          "size": 452
        }
      ],
      "timestamp": "2025-06-17 19:37:09"
    },
    {
      "type": "file_access_security",
      "checks": [
        {
          "check": "inputディレクトリアクセス",
          "status": "safe",
          "details": "アクセス権限が適切に設定されています"
        },
        {
          "check": "データベースファイル保護: archive-index.db",
          "status": "safe",
          "details": "ファイルサイズ: 32768 bytes"
        },
        {
          "check": "データベースファイル保護: learning.db",
          "status": "safe",
          "details": "ファイルサイズ: 106496 bytes"
        },
        {
          "check": "データベースファイル保護: profiles.db",
          "status": "safe",
          "details": "ファイルサイズ: 24576 bytes"
        },
        {
          "check": "outputディレクトリセキュリティ",
          "status": "safe",
          "details": "適切なアクセス制御が設定されています"
        }
      ],
      "timestamp": "2025-06-17 19:37:09"
    },
    {
      "type": "data_integrity",
      "checks": [
        {
          "check": "データベーステーブル数",
          "value": 6,
          "expected": 6,
          "status": "safe"
        },
        {
          "check": "学習パターン数",
          "value": 14,
          "status": "safe"
        },
        {
          "check": "NULL値検証",
          "value": 0,
          "status": "safe"
        },
        {
          "check": "ファイル内容検証: comprehensive_test_data.txt",
          "status": "safe",
          "size": 432
        },
        {
          "check": "ファイル内容検証: constraint_violation_fix.txt",
          "status": "safe",
          "size": 358
        },
        {
          "check": "ファイル内容検証: interactive_workflow_test.txt",
          "status": "safe",
          "size": 423
        },
        {
          "check": "ファイル内容検証: zero-base-test.txt",
          "status": "safe",
          "size": 452
        }
      ],
      "timestamp": "2025-06-17 19:37:09"
    }
  ],
  "designCompliance": {
    "apiKeyNotRequired": true,
    "dialogMode": true,
    "simpleLogging": true,
    "llmCentric": true
  },
  "recommendations": [
    {
      "priority": "low",
      "area": "ファイルアクセス",
      "suggestion": "定期的なファイル権限確認"
    },
    {
      "priority": "medium",
      "area": "データ整合性",
      "suggestion": "定期的なデータベース整合性チェック"
    },
    {
      "priority": "low",
      "area": "依存関係",
      "suggestion": "外部ライブラリの定期的な更新"
    }
  ]
}